fsio/__init__.py
fsio/cli/__init__.py
fsio/cli/program.py
fsio/core/__init__.py
fsio/core/file_type.py
fsio-1.3.7.dist-info/METADATA
fsio-1.3.7.dist-info/WHEEL
fsio-1.3.7.dist-info/entry_points.txt
fsio-1.3.7.dist-info/licenses/LICENSE
fsio-1.3.7.dist-info/RECORD
