Metadata-Version: 2.4
Name: fsio
Version: 1.3.7
Summary: Python package containing useful file system operations
Project-URL: Documentation, https://collier-p-charlie.github.io/fsio
Project-URL: Repository, https://github.com/collier-p-charlie/fsio
Project-URL: Issues, https://github.com/collier-p-charlie/fsio/issues
Project-URL: Changelog, https://github.com/collier-p-charlie/fsio/blob/main/CHANGELOG.md
Author-email: Charlie Collier <collier.p.charlie@gmail.com>
Maintainer-email: Charlie Collier <collier.p.charlie@gmail.com>
License-Expression: MIT
License-File: LICENSE
Classifier: Framework :: Hatch
Classifier: Operating System :: OS Independent
Classifier: Programming Language :: Python :: 3
Requires-Python: >=3.12
Provides-Extra: cli
Requires-Dist: typer; extra == 'cli'
Provides-Extra: docs
Requires-Dist: mkdocs; extra == 'docs'
Requires-Dist: mkdocs-material; extra == 'docs'
Requires-Dist: mkdocstrings[python]; extra == 'docs'
Provides-Extra: test
Requires-Dist: mypy; extra == 'test'
Requires-Dist: pre-commit; extra == 'test'
Requires-Dist: pyarrow; extra == 'test'
Requires-Dist: pytest; extra == 'test'
Requires-Dist: pytest-cov; extra == 'test'
Requires-Dist: ruff; extra == 'test'
